toutatis/__init__.py
toutatis/core.py
toutatis-1.24.dist-info/LICENSE
toutatis-1.24.dist-info/METADATA
toutatis-1.24.dist-info/WHEEL
toutatis-1.24.dist-info/entry_points.txt
toutatis-1.24.dist-info/top_level.txt
toutatis-1.24.dist-info/RECORD
