Metadata-Version: 2.1
Name: toutatis
Version: 1.24
Summary: It is a tool written to retrieve private information such as Phone Number, Mail Address, ID on Instagram accounts via API.
Home-page: http://github.com/megadose/toutatis
Author: megadose
Author-email: UNKNOWN
License: UNKNOWN
Platform: UNKNOWN
Classifier: Programming Language :: Python
Classifier: License :: OSI Approved :: GNU General Public License v3 (GPLv3)
Requires-Dist: argparse
Requires-Dist: httpx
Requires-Dist: tabulate
Requires-Dist: tqdm
Requires-Dist: unicodecsv
